infinitecraft/__init__.py
infinitecraft/__main__.py
infinitecraft/constants.py
infinitecraft/dummies.py
infinitecraft/element.py
infinitecraft/errors.py
infinitecraft/infinitecraft.py
infinitecraft/logger.py
infinitecraft/types.py
infinitecraft/utils.py
infinite_craft-1.1.3.dist-info/LICENSE
infinite_craft-1.1.3.dist-info/METADATA
infinite_craft-1.1.3.dist-info/WHEEL
infinite_craft-1.1.3.dist-info/entry_points.txt
infinite_craft-1.1.3.dist-info/top_level.txt
infinite_craft-1.1.3.dist-info/RECORD
