Metadata-Version: 2.1
Name: infinite-craft
Version: 1.1.3
Summary: An API Wrapper of Neal's Infinite Craft game in Python for people to implement in their programs.
Author: sqdnoises
License: MIT License
Project-URL: Homepage, https://github.com/sqdnoises/infinite-craft
Classifier: Programming Language :: Python :: 3
Classifier: License :: OSI Approved :: MIT License
Classifier: Operating System :: OS Independent
Requires-Python: >=3.10
License-File: LICENSE
Requires-Dist: aiohttp
Requires-Dist: fastapi
Requires-Dist: uvicorn
Provides-Extra: dev
Requires-Dist: pytest ; extra == 'dev'
Requires-Dist: pytest-asyncio ; extra == 'dev'
Requires-Dist: bumpver ; extra == 'dev'
Requires-Dist: pip-tools ; extra == 'dev'
Requires-Dist: build ; extra == 'dev'
Requires-Dist: twine ; extra == 'dev'
